curvaceous/__init__.py
curvaceous/curve.py
curvaceous/interval.py
curvaceous/solvers.py
curvaceous-0.6.0.data/data/VERSION
curvaceous-0.6.0.dist-info/licenses/LICENSE
curvaceous-0.6.0.dist-info/METADATA
curvaceous-0.6.0.dist-info/WHEEL
curvaceous-0.6.0.dist-info/top_level.txt
curvaceous-0.6.0.dist-info/RECORD
