Metadata-Version: 2.4
Name: curvaceous
Version: 0.6.0
Home-page: https://gitlab.com/greenhousegroup/ai/libraries/curvaceous/
Author: Greenhouse AI team
Author-email: ai@greenhousegroup.com
Classifier: Programming Language :: Python :: 3
Classifier: License :: OSI Approved :: MIT License
Classifier: Operating System :: OS Independent
Classifier: Programming Language :: Python :: 3
License-File: LICENSE
Requires-Dist: numpy<3,>=2.3
Requires-Dist: ortools<10,>=9.14.6206
Requires-Dist: pandas<3,>=2.3.1
Dynamic: author
Dynamic: author-email
Dynamic: classifier
Dynamic: description
Dynamic: home-page
Dynamic: keywords
Dynamic: license-file
Dynamic: requires-dist
